Metadata-Version: 1.0
Name: scratch-probability
Version: 0.1
Summary: Gaussian and Binomial distributions
Home-page: UNKNOWN
Author: Sameh Awaida
Author-email: myemail@something.com
License: UNKNOWN
Platform: UNKNOWN
